hanzo/__init__.py
hanzo/__main__.py
hanzo/base_agent.py
hanzo/batch_orchestrator.py
hanzo/cli.py
hanzo/dev.py
hanzo/fallback_handler.py
hanzo/mcp_server.py
hanzo/memory_manager.py
hanzo/model_registry.py
hanzo/orchestrator_config.py
hanzo/rate_limiter.py
hanzo/repl.py
hanzo/streaming.py
hanzo/commands/__init__.py
hanzo/commands/agent.py
hanzo/commands/auth.py
hanzo/commands/auto.py
hanzo/commands/base.py
hanzo/commands/chat.py
hanzo/commands/cloud.py
hanzo/commands/config.py
hanzo/commands/cx.py
hanzo/commands/doc.py
hanzo/commands/env.py
hanzo/commands/events.py
hanzo/commands/flow.py
hanzo/commands/fn.py
hanzo/commands/growth.py
hanzo/commands/iam.py
hanzo/commands/install.py
hanzo/commands/jobs.py
hanzo/commands/k8s.py
hanzo/commands/kv.py
hanzo/commands/mcp.py
hanzo/commands/miner.py
hanzo/commands/ml.py
hanzo/commands/network.py
hanzo/commands/node.py
hanzo/commands/o11y.py
hanzo/commands/platform.py
hanzo/commands/pubsub.py
hanzo/commands/queues.py
hanzo/commands/repl.py
hanzo/commands/router.py
hanzo/commands/run.py
hanzo/commands/search.py
hanzo/commands/secrets.py
hanzo/commands/storage.py
hanzo/commands/tasks.py
hanzo/commands/tools.py
hanzo/commands/vector.py
hanzo/infra/__init__.py
hanzo/infra/cron.py
hanzo/infra/documentdb.py
hanzo/infra/functions.py
hanzo/infra/kv.py
hanzo/infra/pubsub.py
hanzo/infra/queues.py
hanzo/infra/search.py
hanzo/infra/storage.py
hanzo/infra/tasks.py
hanzo/infra/vector.py
hanzo/interactive/__init__.py
hanzo/interactive/dashboard.py
hanzo/interactive/enhanced_repl.py
hanzo/interactive/model_selector.py
hanzo/interactive/repl.py
hanzo/interactive/todo_manager.py
hanzo/router/__init__.py
hanzo/tools/__init__.py
hanzo/tools/detector.py
hanzo/ui/__init__.py
hanzo/ui/inline_startup.py
hanzo/ui/startup.py
hanzo/utils/__init__.py
hanzo/utils/config.py
hanzo/utils/net_check.py
hanzo/utils/output.py
hanzo-0.3.48.dist-info/METADATA
hanzo-0.3.48.dist-info/WHEEL
hanzo-0.3.48.dist-info/entry_points.txt
hanzo-0.3.48.dist-info/RECORD
