Metadata-Version: 2.4
Name: hanzo
Version: 0.3.48
Summary: Hanzo AI - Complete AI Infrastructure Platform with CLI, Router, MCP, and Agent Runtime
Project-URL: Homepage, https://hanzo.ai
Project-URL: Repository, https://github.com/hanzoai/python-sdk
Project-URL: Documentation, https://docs.hanzo.ai/cli
Project-URL: Bug Tracker, https://github.com/hanzoai/python-sdk/issues
Author-email: Hanzo AI <dev@hanzo.ai>
Keywords: agents,ai,cli,hanzo,llm,local-ai,mcp,private-ai
Classifier: Development Status :: 4 - Beta
Classifier: Environment :: Console
Classifier: Intended Audience :: Developers
Classifier: License :: OSI Approved :: Apache Software License
Classifier: Operating System :: OS Independent
Classifier: Programming Language :: Python :: 3
Classifier: Programming Language :: Python :: 3.12
Classifier: Programming Language :: Python :: 3.13
Classifier: Topic :: Scientific/Engineering :: Artificial Intelligence
Classifier: Topic :: Software Development :: Libraries :: Python Modules
Requires-Python: >=3.12
Requires-Dist: anthropic>=0.25.0
Requires-Dist: click>=8.1.0
Requires-Dist: httpx>=0.23.0
Requires-Dist: openai>=1.0.0
Requires-Dist: prompt-toolkit>=3.0.0
Requires-Dist: pydantic>=2.0.0
Requires-Dist: pyyaml>=6.0
Requires-Dist: qrcode>=7.4.2
Requires-Dist: rich>=13.0.0
Requires-Dist: typer>=0.9.0
Provides-Extra: agents
Requires-Dist: hanzo-agents>=0.1.0; extra == 'agents'
Requires-Dist: hanzo-network>=0.1.3; extra == 'agents'
Provides-Extra: ai
Requires-Dist: hanzoai>=1.0.0; extra == 'ai'
Provides-Extra: all
Requires-Dist: hanzo-aci>=0.2.8; extra == 'all'
Requires-Dist: hanzo-agents>=0.1.0; extra == 'all'
Requires-Dist: hanzo-mcp>=0.7.0; extra == 'all'
Requires-Dist: hanzo-memory>=1.0.0; extra == 'all'
Requires-Dist: hanzo-network>=0.1.3; extra == 'all'
Requires-Dist: hanzo-repl>=0.1.0; extra == 'all'
Requires-Dist: hanzoai>=1.0.0; extra == 'all'
Provides-Extra: cron
Requires-Dist: croniter>=2.0.0; extra == 'cron'
Requires-Dist: redis>=5.0.0; extra == 'cron'
Provides-Extra: dev
Requires-Dist: hanzo-aci>=0.2.8; extra == 'dev'
Provides-Extra: documentdb
Requires-Dist: motor>=3.3.0; extra == 'documentdb'
Requires-Dist: pymongo>=4.6.0; extra == 'documentdb'
Provides-Extra: functions
Requires-Dist: httpx>=0.23.0; extra == 'functions'
Provides-Extra: infra
Requires-Dist: aiobotocore>=2.9.0; extra == 'infra'
Requires-Dist: botocore>=1.34.0; extra == 'infra'
Requires-Dist: croniter>=2.0.0; extra == 'infra'
Requires-Dist: httpx>=0.23.0; extra == 'infra'
Requires-Dist: meilisearch-python-sdk>=3.0.0; extra == 'infra'
Requires-Dist: motor>=3.3.0; extra == 'infra'
Requires-Dist: nats-py>=2.6.0; extra == 'infra'
Requires-Dist: pymongo>=4.6.0; extra == 'infra'
Requires-Dist: qdrant-client>=1.7.0; extra == 'infra'
Requires-Dist: redis>=5.0.0; extra == 'infra'
Requires-Dist: temporalio>=1.4.0; extra == 'infra'
Provides-Extra: kv
Requires-Dist: redis>=5.0.0; extra == 'kv'
Provides-Extra: mcp
Requires-Dist: hanzo-mcp>=0.7.0; extra == 'mcp'
Provides-Extra: pubsub
Requires-Dist: nats-py>=2.6.0; extra == 'pubsub'
Provides-Extra: queues
Requires-Dist: redis>=5.0.0; extra == 'queues'
Provides-Extra: repl
Requires-Dist: hanzo-repl>=0.1.0; extra == 'repl'
Provides-Extra: router
Provides-Extra: search
Requires-Dist: meilisearch-python-sdk>=3.0.0; extra == 'search'
Provides-Extra: storage
Requires-Dist: aiobotocore>=2.9.0; extra == 'storage'
Requires-Dist: botocore>=1.34.0; extra == 'storage'
Provides-Extra: tasks
Requires-Dist: temporalio>=1.4.0; extra == 'tasks'
Provides-Extra: vector
Requires-Dist: qdrant-client>=1.7.0; extra == 'vector'
